aws_rds_manager-1.0.3.dist-info/DESCRIPTION.rst
aws_rds_manager-1.0.3.dist-info/METADATA
aws_rds_manager-1.0.3.dist-info/RECORD
aws_rds_manager-1.0.3.dist-info/WHEEL
aws_rds_manager-1.0.3.dist-info/entry_points.txt
aws_rds_manager-1.0.3.dist-info/metadata.json
aws_rds_manager-1.0.3.dist-info/top_level.txt
awsrdsmanager/__init__.py
awsrdsmanager/__main__.py
awsrdsmanager/base.py
awsrdsmanager/sunsetrdssnapshots.py
