Metadata-Version: 2.0
Name: aws-rds-manager
Version: 1.0.3
Summary: CLI tool providing sunsetting of RDS snapshots
Home-page: https://github.com/drewsonne/aws-rds-manager
Author: Drew J. Sonne
Author-email: drew.sonne@gmail.com
License: GPLv2
Platform: UNKNOWN
Classifier: Development Status :: 5 - Production/Stable
Classifier: Environment :: Console
Classifier: Intended Audience :: System Administrators
Classifier: Intended Audience :: Developers
Classifier: Intended Audience :: Information Technology
Classifier: License :: OSI Approved :: GNU General Public License v2 (GPLv2)
Classifier: Natural Language :: English
Classifier: Operating System :: MacOS :: MacOS X
Classifier: Operating System :: POSIX :: Linux
Classifier: Programming Language :: Python :: 2.7
Classifier: Programming Language :: Python :: 3.4
Classifier: Topic :: Database
Classifier: Topic :: System :: Archiving :: Backup
Requires-Dist: aws-auth-helper
Requires-Dist: six
